proxy_rotator/__init__.py
proxy_rotator/config.py
proxy_rotator/errors.py
proxy_rotator/models.py
proxy_rotator/process.py
proxy_rotator/py.typed
proxy_rotator/rotator.py
proxy_rotator/subscription.py
proxy_rotator/user_agents.py
proxy_rotator/utils.py
proxy_rotator/protocols/__init__.py
proxy_rotator/protocols/vmess.py
xray_proxy_rotator-0.1.0.dist-info/licenses/LICENSE
xray_proxy_rotator-0.1.0.dist-info/METADATA
xray_proxy_rotator-0.1.0.dist-info/WHEEL
xray_proxy_rotator-0.1.0.dist-info/top_level.txt
xray_proxy_rotator-0.1.0.dist-info/RECORD
