Metadata-Version: 2.4
Name: xray-proxy-rotator
Version: 0.1.0
Summary: Async VMESS proxy rotation manager with automatic subscription updates and connection testing
Author-email: Keyhan Kamyar <keyhankamyar@gmail.com>
Maintainer-email: Keyhan Kamyar <keyhankamyar@gmail.com>
License: MIT
Project-URL: Homepage, https://github.com/keyhankamyar/ProxyRotator
Project-URL: Documentation, https://github.com/keyhankamyar/ProxyRotator#readme
Project-URL: Repository, https://github.com/keyhankamyar/ProxyRotator
Project-URL: Issues, https://github.com/keyhankamyar/ProxyRotator/issues
Project-URL: Changelog, https://github.com/keyhankamyar/ProxyRotator/blob/main/CHANGELOG.md
Keywords: proxy,vmess,rotation,xray,scraping,async,subscription,proxy-rotation,web-scraping
Classifier: Development Status :: 3 - Alpha
Classifier: Intended Audience :: Developers
Classifier: License :: OSI Approved :: MIT License
Classifier: Operating System :: OS Independent
Classifier: Programming Language :: Python :: 3
Classifier: Programming Language :: Python :: 3.11
Classifier: Programming Language :: Python :: 3.12
Classifier: Programming Language :: Python :: 3 :: Only
Classifier: Topic :: Internet :: Proxy Servers
Classifier: Topic :: Software Development :: Libraries :: Python Modules
Classifier: Typing :: Typed
Classifier: Framework :: AsyncIO
Requires-Python: >=3.11
License-File: LICENSE
Requires-Dist: httpx>=0.27.0
Requires-Dist: pydantic>=2.0.0
Requires-Dist: pydantic-settings>=2.0.0
Provides-Extra: dev
Requires-Dist: pytest>=8.0.0; extra == "dev"
Requires-Dist: pytest-asyncio>=0.23.0; extra == "dev"
Requires-Dist: pytest-cov>=4.1.0; extra == "dev"
Requires-Dist: black>=24.0.0; extra == "dev"
Requires-Dist: ruff>=0.3.0; extra == "dev"
Requires-Dist: mypy>=1.9.0; extra == "dev"
Requires-Dist: pre-commit>=3.6.0; extra == "dev"
Requires-Dist: build>=1.0.0; extra == "dev"
Requires-Dist: twine>=5.0.0; extra == "dev"
Provides-Extra: docs
Requires-Dist: mkdocs>=1.5.0; extra == "docs"
Requires-Dist: mkdocs-material>=9.5.0; extra == "docs"
Requires-Dist: mkdocstrings[python]>=0.24.0; extra == "docs"
Dynamic: license-file
